cimpyorm/Parser.py
cimpyorm/Writer.py
cimpyorm/__init__.py
cimpyorm/api.py
cimpyorm/auxiliary.py
cimpyorm/backends.py
cimpyorm/cli.py
cimpyorm/datasets.py
cimpyorm/Model/Parseable.py
cimpyorm/Model/Schema.py
cimpyorm/Model/Source.py
cimpyorm/Model/__init__.py
cimpyorm/Model/auxiliary.py
cimpyorm/Model/Elements/Base.py
cimpyorm/Model/Elements/Class.py
cimpyorm/Model/Elements/Datatype.py
cimpyorm/Model/Elements/Enum.py
cimpyorm/Model/Elements/Property.py
cimpyorm/Model/Elements/__init__.py
cimpyorm/Test/__init__.py
cimpyorm/Test/conftest.py
cimpyorm/Test/test_api.py
cimpyorm/Test/test_aux_and_misc.py
cimpyorm/Test/test_data_integrity.py
cimpyorm/Test/test_loadRDFS_pytest.py
cimpyorm/Test/test_metadata.py
cimpyorm/Test/test_parser.py
cimpyorm/Test/test_schema.py
cimpyorm/Test/test_serialization.py
cimpyorm/Test/test_xml_merge.py
cimpyorm/Test/Deployment/__init__.py
cimpyorm/Test/Deployment/test_pypi_deploy.py
cimpyorm/Test/Integration/__init__.py
cimpyorm/Test/Integration/MariaDB/__init__.py
cimpyorm/Test/Integration/MariaDB/test_integration_tests.py
cimpyorm/Test/Integration/MySQL/__init__.py
cimpyorm/Test/Integration/MySQL/test_integration_tests.py
cimpyorm/Test/Integration/SQLite/__init__.py
cimpyorm/Test/Integration/SQLite/test_integration_tests.py
cimpyorm/Test/test_datasets/__init__.py
cimpyorm/res/datasets/FullGrid/20171002T0930Z_1D_BE_SSH_4.xml
cimpyorm/res/datasets/FullGrid/20171002T0930Z_1D_BE_SV_4.xml
cimpyorm/res/datasets/FullGrid/20171002T0930Z_1D_BE_TP_4.xml
cimpyorm/res/datasets/FullGrid/20171002T0930Z_BE_EQ_4.xml
cimpyorm/res/datasets/MiniGrid_BusBranch/MiniGridTestConfiguration_BC_DL_v3.0.0.xml
cimpyorm/res/datasets/MiniGrid_BusBranch/MiniGridTestConfiguration_BC_EQ_v3.0.0.xml
cimpyorm/res/datasets/MiniGrid_BusBranch/MiniGridTestConfiguration_BC_SSH_v3.0.0.xml
cimpyorm/res/datasets/MiniGrid_BusBranch/MiniGridTestConfiguration_BC_SV_v3.0.0.xml
cimpyorm/res/datasets/MiniGrid_BusBranch/MiniGridTestConfiguration_BC_TP_v3.0.0.xml
cimpyorm-0.10.1.dist-info/LICENSE
cimpyorm-0.10.1.dist-info/METADATA
cimpyorm-0.10.1.dist-info/WHEEL
cimpyorm-0.10.1.dist-info/entry_points.txt
cimpyorm-0.10.1.dist-info/top_level.txt
cimpyorm-0.10.1.dist-info/RECORD
