Metadata-Version: 2.1
Name: cimpyorm
Version: 0.10.1
Summary: A database-backed ORM for CIM datasets.
Home-page: http://www.iaew.rwth-aachen.de
Author: Thomas Offergeld
Author-email: t.offergeld@iaew.rwth-aachen.de
Project-URL: homepage, http://www.iaew.rwth-aachen.de
Classifier: Development Status :: 3 - Alpha
Classifier: Intended Audience :: Developers
Classifier: Intended Audience :: Science/Research
Classifier: License :: OSI Approved :: BSD License
Classifier: Natural Language :: English
Classifier: Operating System :: OS Independent
Classifier: Programming Language :: Python :: 3
Classifier: Programming Language :: Python :: 3.9
Classifier: Programming Language :: Python :: 3.10
Classifier: Programming Language :: Python :: 3.11
License-File: LICENSE
Requires-Dist: Click
Requires-Dist: sqlalchemy
Requires-Dist: networkx
Requires-Dist: numpy
Requires-Dist: lxml
Requires-Dist: pandas
Requires-Dist: tabulate
Requires-Dist: tqdm
Requires-Dist: defusedxml <0.7.0
